[
    {
        "event_id": "290628",
        "cover_image": "https://s2.showstart.com/img/2026/0214/14/30/75e764381aa3492f9173c04d268e3ce3_841_1159_792852.0x0.jpg",
        "title": "2026阜阳斑马音乐节",
        "price": "¥199起",
        "time": "2026/03/29 13:00",
        "event_url": "https://www.showstart.com/event/290628",
        "artist": "新裤子/痛仰/梁博/二手玫瑰乐队/棱镜/夏日入侵企画/舌头乐队/白日密语/野肆乐队/丑橘出逃乐队/梅卡德尔乐队",
        "address": "安徽省阜阳市颍州区裕安路与南屏路交叉口",
        "detail_time": "03月29日 13:00-03月29日 21:00",
        "venue": "阜阳 斑马音乐节草坪",
        "styles": [
            "流行",
            "摇滚",
            "独立"
        ],
        "content_html": "<p style=\"text-align: center;\"><img src=\"https://s2.showstart.com/img/2026/0225/15/00/a37a5098782945d5be49ac98fc14ac02_1260_12931_8157503.0x0.jpg?imageMogr2/thumbnail/640x/gravity/Center/crop/640x\" alt=\"\"></p>\n<p style=\"text-align: center;\"><img src=\"https://s2.showstart.com/img/2026/0224/13/30/633bbb8bdbc043aba5fc0c44d5c83eea_1074_1820_1295709.0x0.png?imageMogr2/thumbnail/640x/gravity/Center/crop/640x\" alt=\"\" width=\"640\" height=\"1085\"></p>\n<p style=\"text-align: center;\">声动淮水·乐聚颍州<br>春风渡淮水，音符跃暖城<br>3月21日起，斑马精酿 × QQ音乐 联袂巨献</p>\n<p style=\"text-align: center;\">巅峰之约，共赴阜阳春日乐章！<br>持续解锁阜阳多日音乐盛宴，敬请期待...<br>📍 地点：安徽省阜阳市斑马音乐节草坪</p>\n<p style=\"text-align: center;\"><img src=\"https://s2.showstart.com/img/2026/0226/10/00/fd3c25b5031e4635a8ab5319b3f0ea9f_1274_2155_2275635.0x0.png?imageMogr2/thumbnail/640x/gravity/Center/crop/640x\" alt=\"\"><img src=\"https://s2.showstart.com/img/2026/0226/10/00/bb96c9c72b3e4bce996283dba406fba8_540_9099_5335195.0x0.png?imageMogr2/thumbnail/640x/gravity/Center/crop/640x\" alt=\"\"></p>"
    },
    {
        "event_id": "293064",
        "cover_image": "https://s2.showstart.com/img/2026/0320/12/00/fe2017cbc4394cb3a5716140b02479f2_600_800_380467.0x0.jpg",
        "title": "2026西安张冠李戴音乐节",
        "price": "¥399起",
        "time": "2026/04/18 14:00",
        "event_url": "https://www.showstart.com/event/293064",
        "artist": "崔健/DOUDOU（杜冰儿、杜飞儿）/FKJ（French Kiwi Juice）/Kerala Dust/犬儒/石岩/逃跑计划/惘闻/岛屿心情",
        "address": "陕西省西安市新城区大明宫国家遗址公园御道广场",
        "detail_time": "04月18日 14:00-04月18日 22:00",
        "venue": "西安 大明宫遗址公园御道广场",
        "styles": [
            "摇滚",
            "独立"
        ],
        "content_html": "<p style=\"text-align: center;\"><span style=\"font-size: 24px;\"><strong>2026西安张冠李戴音乐节</strong></span></p>\n<p style=\"text-align: center;\"><span style=\"font-size: 18px; color: #e67e23;\"><strong>3月30日（周一）11:18</strong></span></p>\n<p style=\"text-align: center;\"><span style=\"font-size: 18px;\"><strong>普通区·特惠单日票抢先抢</strong></span></p>\n<p style=\"text-align: center;\"><span style=\"font-size: 18px; color: #e67e23;\"><strong>3月30日（周一）12:18</strong></span></p>\n<p style=\"text-align: center;\"><span style=\"font-size: 18px;\"><strong>全平台预售开启</strong></span></p>\n<p style=\"text-align: center;\"><span style=\"font-size: 18px;\"><strong><img src=\"https://s2.showstart.com/img/2026/0327/12/00/7cd0871658324e7f806074b6cc41e59d_1080_1123_891910.0x0.png?imageMogr2/thumbnail/640x/gravity/Center/crop/640x\" alt=\"\" width=\"640\" height=\"665\"></strong></span></p>\n<p style=\"text-align: center;\"><span style=\"font-size: 24px; color: #e67e23;\"><strong>票价公布</strong></span></p>\n<p style=\"text-align: center;\">&nbsp;</p>\n<p style=\"text-align: center;\"><span style=\"color: #e67e23;\"><strong><u>普通区</u></strong></span></p>\n<p style=\"text-align: center;\">特惠单日票&nbsp;<strong>￥199</strong></p>\n<p style=\"text-align: center;\">预售单日票&nbsp;<strong>￥399</strong></p>\n<p style=\"text-align: center;\">全价单日票&nbsp;<strong>￥499</strong></p>\n<p style=\"text-align: center;\">双日通票&nbsp;<strong>￥758</strong></p>\n<p style=\"text-align: center;\">&nbsp;</p>\n<p style=\"text-align: center;\"><span style=\"color: #e67e23;\"><strong><u>前排区</u></strong></span></p>\n<p style=\"text-align: center;\">单日票&nbsp;<strong>￥588</strong></p>\n<h3 style=\"text-align: center;\"><strong><img src=\"https://s2.showstart.com/img/2026/0327/12/30/9f7406de2ab84623bd5e149b7637ab2d_1080_2070_1736692.0x0.png?imageMogr2/thumbnail/640x/gravity/Center/crop/640x\" alt=\"\" width=\"640\" height=\"1227\"></strong></h3>\n<p><strong><img style=\"display: block; margin-left: auto; margin-right: auto;\" src=\"https://s2.showstart.com/img/2026/0327/12/30/f7855b87ce2b4a23861afb4849b46747_1080_1080_851070.0x0.png?imageMogr2/thumbnail/640x/gravity/Center/crop/640x\" alt=\"\" width=\"640\" height=\"640\"></strong></p>\n<h3 style=\"text-align: center;\"><strong><img src=\"https://s2.showstart.com/img/2026/0327/12/30/95a9a23b62cc4b28aaafc146b80782f0_1080_1890_954548.0x0.png?imageMogr2/thumbnail/640x/gravity/Center/crop/640x\" alt=\"\" width=\"640\" height=\"1120\"></strong></h3>\n<h3 style=\"text-align: center;\"><strong><img src=\"https://s2.showstart.com/img/2026/0327/12/30/aa3b0b119a5d4e4e990391d5a41cea8e_2500_4375_2894405.0x0.png?imageMogr2/thumbnail/640x/gravity/Center/crop/640x\" alt=\"\" width=\"640\" height=\"1120\"></strong></h3>\n<h3 style=\"text-align: center;\"><strong><img src=\"https://s2.showstart.com/img/2026/0327/12/30/7f3fa4cbc0184e10911147b616bd219b_1080_1227_539982.0x0.png?imageMogr2/thumbnail/640x/gravity/Center/crop/640x\" alt=\"\" width=\"640\" height=\"727\"></strong></h3>\n<h3 style=\"text-align: center;\"><strong><img src=\"https://s2.showstart.com/img/2026/0327/12/30/6a516e0f20474f7ab31b4b5f0742607c_814_2134_1016246.0x0.png?imageMogr2/thumbnail/640x/gravity/Center/crop/640x\" alt=\"\" width=\"640\" height=\"1678\"></strong></h3>\n<p style=\"text-align: center;\"><span style=\"color: #e67e23; font-size: 24px;\"><strong>演出时间表择日公布</strong></span></p>\n<p style=\"text-align: center;\"><span style=\"color: #e67e23; font-size: 24px;\"><strong>敬请期待</strong></span></p>\n<p style=\"text-align: center;\"><span style=\"color: #e67e23; font-size: 24px;\">-</span></p>\n<p style=\"text-align: center;\">&nbsp;</p>\n<p style=\"text-align: center;\">张冠李戴早已不是一场音乐节</p>\n<p style=\"text-align: center;\">是情怀，也是初心</p>\n<p style=\"text-align: center;\">因为懂得</p>\n<p style=\"text-align: center;\">所以更加独特</p>\n<p style=\"text-align: center;\">&nbsp;</p>\n<p style=\"text-align: center;\"><strong>阔别再聚</strong></p>\n<p style=\"text-align: center;\"><strong>这次我们依旧</strong></p>\n<p style=\"text-align: center;\"><strong>现场见</strong></p>\n<p style=\"text-align: center;\">&nbsp;</p>\n<h3><strong><img style=\"display: block; margin-left: auto; margin-right: auto;\" src=\"https://s2.showstart.com/img/2026/0320/13/00/b65634be9ddd422eaf8f84fd0b09bfa2_1256_1820_3559208.0x0.png?imageMogr2/thumbnail/640x/gravity/Center/crop/640x\" alt=\"\" width=\"640\" height=\"927\"></strong></h3>\n<p style=\"text-align: center;\">&nbsp;</p>\n<p style=\"text-align: center;\"><span style=\"font-size: 16px;\"><strong>情怀与先锋共生</strong></span></p>\n<p style=\"text-align: center;\"><span style=\"font-size: 16px;\"><strong>摇滚与电子同频</strong></span></p>\n<p style=\"text-align: center;\">这份承载着11年期待的阵容名单</p>\n<p style=\"text-align: center;\">每一组都诚意满满</p>\n<p style=\"text-align: center;\">每一段旋律都值得奔赴</p>\n<h2 style=\"text-align: center;\"><img src=\"https://s2.showstart.com/img/2026/0327/12/30/203fa535a9fb41869ac2e61eae194e59_900_1200_1318072.0x0.png?imageMogr2/thumbnail/640x/gravity/Center/crop/640x\" alt=\"\" width=\"640\" height=\"853\"></h2>\n<p style=\"text-align: center;\">&nbsp;</p>\n<h2 style=\"text-align: center;\"><strong>- 国际声音 重磅加盟 -</strong></h2>\n<h2 style=\"text-align: center;\"><strong>&nbsp;</strong></h2>\n<h2 style=\"text-align: center;\"><strong>&nbsp;4月19日&nbsp;</strong></h2>\n<h2 style=\"text-align: center;\"><strong><u>Slowdive</u></strong></h2>\n<p style=\"text-align: center;\"><img src=\"https://s2.showstart.com/img/2026/0320/12/00/eb65e8bcc81e4c9aa5bdfbd731fd48b9_1080_1620_2717435.0x0.png?imageMogr2/thumbnail/640x/gravity/Center/crop/640x\" alt=\"\"></p>\n<p style=\"text-align: center;\">盯鞋自赏摇滚（Shoegaze）的传奇乐队。被誉为盯鞋三巨头之一，连接着盯鞋的过去与现在。时隔8年再次来华，参演西安张冠李戴音乐节，也是国内唯一一场音乐节，他们将奉献一场60分钟的梦幻演出。</p>\n<p style=\"text-align: center;\">&nbsp;</p>\n<h2 style=\"text-align: center;\"><strong>&nbsp;4月18日&nbsp;</strong></h2>\n<h2 style=\"text-align: center;\"><strong><u>FKJ</u></strong></h2>\n<p style=\"text-align: center;\"><img src=\"https://s2.showstart.com/img/2026/0320/12/00/568657302b6e4f579f57c3ec6495d75b_1080_1620_2472587.0x0.png?imageMogr2/thumbnail/640x/gravity/Center/crop/640x\" alt=\"\"></p>\n<p style=\"text-align: center;\">法国天才电子音乐制作人，New French House领军人物。现场演出常以即兴Live Set构建迷人音景，并且拥有“一人一乐队”美称，深受电子和独立音乐爱好者喜爱。此次是FKJ时隔两年再次来到中国，在西安张冠李戴音乐节的舞台上，为大家奉献75分钟的超长Live set。</p>\n<p style=\"text-align: center;\">&nbsp;</p>\n<h2 style=\"text-align: center;\"><strong>&nbsp;4月19日&nbsp;</strong></h2>\n<h2 style=\"text-align: center;\"><strong><u>Motorama</u></strong></h2>\n<h3 style=\"text-align: center;\"><strong>&nbsp;<img src=\"https://s2.showstart.com/img/2026/0320/12/00/4c2ce2219b5946e89befc45a0c6fce50_831_1247_1777440.0x0.png?imageMogr2/thumbnail/640x/gravity/Center/crop/640x\" alt=\"\"></strong></h3>\n<p style=\"text-align: center;\">俄罗斯后朋克乐队。以清冷旋律、诗意歌词与独特东欧氛围著称。出道至今发行7张专辑、15首单曲。乐队受苏联美学的影响，极致创作追求与独特音乐表达，在全球不断积累乐迷。</p>\n<p style=\"text-align: center;\">&nbsp;</p>\n<h2 style=\"text-align: center;\"><strong>&nbsp;4月18日&nbsp;</strong></h2>\n<h2 style=\"text-align: center;\"><strong><u>Kerala Dust</u></strong></h2>\n<h3 style=\"text-align: center;\"><strong>&nbsp;<img src=\"https://s2.showstart.com/img/2026/0320/12/00/1029066881414993b127ddc31008492a_917_1376_2998209.0x0.png?imageMogr2/thumbnail/640x/gravity/Center/crop/640x\" alt=\"\" width=\"640\" height=\"960\"></strong></h3>\n<p style=\"text-align: center;\">乐队于2016年在伦敦成立，将艺术摇滚与前卫电子相结合。他们的现场演出是对录音室声音的持续对话，2017年首次巡演以来，已完成超150场国际演出，今年首次登陆西安。</p>\n<p style=\"text-align: center;\">&nbsp;</p>\n<h2 style=\"text-align: center;\"><strong>- 摇滚矩阵 先锋同频 -</strong></h2>\n<p style=\"text-align: center;\">&nbsp;</p>\n<h2 style=\"text-align: center;\"><strong>&nbsp;4月18日&nbsp;</strong></h2>\n<h2 style=\"text-align: center;\"><strong><u>崔健</u></strong></h2>\n<p style=\"text-align: center;\"><img src=\"https://s2.showstart.com/img/2026/0320/12/00/26f6955968bb45b1a7383ae71c80edd7_1080_1620_1458694.0x0.png?imageMogr2/thumbnail/640x/gravity/Center/crop/640x\" alt=\"\"></p>\n<p style=\"text-align: center;\">作为中国摇滚的先行者，崔健更是中国摇滚乐四十年发展的奠基者与领航者，是当代文化中极具分量的标志性人物。他以开创性的音乐表达划破时代，拉开中国摇滚乐的序幕，始终用爆发力拉满、感染力十足的现场，传递摇滚最本真、最炽热的精神内核。</p>\n<p style=\"text-align: center;\">恰逢中国摇滚四十周年这一重要节点，崔健将重磅赴约西安，与万千乐迷共赴一场跨越时代、致敬热爱与信仰的摇滚盛宴。</p>\n<p style=\"text-align: center;\">&nbsp;</p>\n<h2 style=\"text-align: center;\"><strong><u>逃跑计划</u></strong></h2>\n<p style=\"text-align: center;\"><img src=\"https://s2.showstart.com/img/2026/0320/12/00/9562a71244a24895ab33511aaa2c118a_1080_1620_2235086.0x0.png?imageMogr2/thumbnail/640x/gravity/Center/crop/640x\" alt=\"\"></p>\n<p style=\"text-align: center;\">逃跑计划乐队是中国主流摇滚乐坛中备受瞩目的乐队之一。乐队以独立流行（Indie Pop）为基调，巧妙融入电子、新浪潮（New Wave）、后朋克（Post Punk）等多种音乐元素，在保持旋律唯美动人的同时，注入了鲜明的时代气息。他们的音乐充满激情与活力又不失温柔浪漫，被广泛认为是国内最具代表性的英式风格乐队之一。</p>\n<p style=\"text-align: center;\">&nbsp;</p>\n<p style=\"text-align: center;\">&nbsp;</p>\n<h2 style=\"text-align: center;\"><span style=\"font-size: 24px;\"><strong><u>惘闻WANGWEN</u></strong></span></h2>\n<p style=\"text-align: center;\"><img src=\"https://s2.showstart.com/img/2026/0320/12/00/32da18c0c93a4d3a85e1b19e8c2f6840_974_1461_1626151.0x0.png?imageMogr2/thumbnail/640x/gravity/Center/crop/640x\" alt=\"\"></p>\n<p style=\"text-align: center;\"><span style=\"font-size: 14px;\">中国器乐摇滚领军乐队，其音乐极具叙事感，如同一部部没有画面的“声音电影”，层层递进的编曲堆叠出磅礴音墙，精准传递复杂难言的情绪，是中国摇滚乐中特别的存在。4月18日惘闻WANG WEN将再次携曜爆甘弦乐团来到西安，为乐迷奉献长达75分钟的史诗级现场。</span></p>\n<p style=\"text-align: center;\">&nbsp;</p>\n<h2 style=\"text-align: center;\"><strong><u>DOUDOU</u></strong></h2>\n<h2 style=\"text-align: center;\"><strong>&nbsp;<img src=\"https://s2.showstart.com/img/2026/0320/12/00/d78d29ab970b4179b45f930e2d490401_1080_1620_2708943.0x0.png?imageMogr2/thumbnail/640x/gravity/Center/crop/640x\" alt=\"\"></strong></h2>\n<p style=\"text-align: center;\">DOUDOU 将东方美学的气息化作音律的叙事，让现代电子音乐的脉冲在传统仪式元素中呼吸、生长。她们以先锋电子为媒，轻盈穿梭于流行与先锋之间，在层层递进的声景中，描摹次世代细腻而真实的情绪流动——不安、柔软、炽热彼此交织，最终汇入一个远古、奇幻、又未来的感知世界。</p>\n<p style=\"text-align: center;\">&nbsp;</p>\n<h2 style=\"text-align: center;\"><span style=\"font-size: 24px;\"><strong><u>岛屿心情</u></strong></span></h2>\n<p style=\"text-align: center;\"><img src=\"https://s2.showstart.com/img/2026/0320/12/00/fbbb741b03c9423b8a21ebc24ba66219_1080_1620_2759282.0x0.png?imageMogr2/thumbnail/640x/gravity/Center/crop/640x\" alt=\"\"></p>\n<p style=\"text-align: center;\"><span style=\"font-size: 14px;\">岛屿心情的音乐以 Indie Pop/Rock 为核心，不受单一风格桎梏，将英伦摇滚的旋律感、后朋克的先锋性、民谣的人文叙事深度融合，风格自由奔放，现场带来极具冲击力的释放感。时隔 17 年，乐队将再度登上张冠李戴音乐节的舞台。</span></p>\n<p style=\"text-align: center;\">&nbsp;</p>\n<h2 style=\"text-align: center;\"><span style=\"font-size: 24px;\"><strong><u>犬儒</u></strong></span></h2>\n<p style=\"text-align: center;\"><span style=\"font-size: 14px;\"><img src=\"https://s2.showstart.com/img/2026/0320/12/00/1563cdea6bf14445bf9ac190fb431277_1080_1620_1997856.0x0.png?imageMogr2/thumbnail/640x/gravity/Center/crop/640x\" alt=\"\"></span></p>\n<p style=\"text-align: center;\"><span style=\"font-size: 14px;\">2022年成立于贵州贵阳，中国新生代乐队。六位不同行业的年轻人因为音乐走到一起，以年轻人的视角观察生活中的大小点滴。2023年上半年发行EP《犬儒》而被大众熟知，同年下半年发行EP《旧情歌》，24年发行了首张录音室专辑《天才艺术家》。曲风在继承了千禧年摇滚乐的同时也在向合成器及弦乐领域不断探索。</span></p>\n<p style=\"text-align: center;\">&nbsp;</p>\n<h2 style=\"text-align: center;\"><span style=\"font-size: 24px;\"><strong><u>石岩</u></strong></span></h2>\n<p style=\"text-align: center;\"><img src=\"https://s2.showstart.com/img/2026/0320/12/00/087522ed554b40bda32f7f663463a2fd_1080_1620_1266138.0x0.png?imageMogr2/thumbnail/640x/gravity/Center/crop/640x\" alt=\"\" width=\"640\" height=\"960\"></p>\n<p style=\"text-align: center;\">全能型独立摇滚音乐人，糅合摇滚、电子、民谣等多元风格，兼具深刻的人文视角与极具冲击力的情绪张力。常年高频巡演的打磨，让他拥有如刀锋般锋利的现场表现力，能为乐迷带来极具沉浸感的极致视听体验。</p>\n<p style=\"text-align: center;\">&nbsp;</p>\n<h2 style=\"text-align: center;\"><strong>&nbsp;4月19日&nbsp;</strong></h2>\n<h2 style=\"text-align: center;\"><span style=\"font-size: 24px;\"><strong><u>痛仰</u></strong></span></h2>\n<p style=\"text-align: center;\"><img src=\"https://s2.showstart.com/img/2026/0320/12/00/45fe2543577b41b9af3cc73da26ac0a2_1080_1620_1663361.0x0.png?imageMogr2/thumbnail/640x/gravity/Center/crop/640x\" alt=\"\"></p>\n<p style=\"text-align: center;\"><span style=\"font-size: 14px;\">痛仰的现场是摇滚精神的完美容器，既能引爆万人合唱的狂欢热浪，又能在细腻的声场处理下，营造出极具深度的沉浸氛围。这种刚柔并济、动静皆宜的现场特质，完美承载了他们跨越边界的音乐表达。</span></p>\n<p style=\"text-align: center;\">&nbsp;</p>\n<h2 style=\"text-align: center;\"><span style=\"font-size: 24px;\"><strong><u>梁博</u></strong></span></h2>\n<p style=\"text-align: center;\"><img src=\"https://s2.showstart.com/img/2026/0320/12/00/bf331217ae3946f386447944a2bbcbad_827_1241_1655253.0x0.png?imageMogr2/thumbnail/640x/gravity/Center/crop/640x\" alt=\"\"></p>\n<p style=\"text-align: center;\"><span style=\"font-size: 14px;\">中国内地男歌手、音乐唱作人。代表作有《男孩》《出现又离开》《日落大道》《曾经是情侣》《黑夜中》《避世离俗》《安然无恙》《苦与乐》等。</span></p>\n<p style=\"text-align: center;\">&nbsp;</p>\n<h2 style=\"text-align: center;\"><span style=\"font-size: 24px;\"><strong><u>贰佰</u></strong></span></h2>\n<p style=\"text-align: center;\"><img src=\"https://s2.showstart.com/img/2026/0320/12/00/83796204faf64186bec6ae1ad05a823d_1080_1620_1065651.0x0.png?imageMogr2/thumbnail/640x/gravity/Center/crop/640x\" alt=\"\"></p>\n<p style=\"text-align: center;\">来自内蒙古阿拉善的民谣唱作人，以烟火气为底色，用质朴沙哑的嗓音与细腻写实的叙事，勾勒普通人的生活日常与内心情绪。他的音乐扎根人间，将生活的烟火、青春的迷茫与心底的倔强揉进旋律，真诚克制，自带治愈力量，在民谣领域里形成极具辨识度的温暖表达。</p>\n<p style=\"text-align: center;\">&nbsp;</p>\n<h2 style=\"text-align: center;\"><span style=\"font-size: 24px;\"><strong><u>声音玩具</u></strong></span></h2>\n<p style=\"text-align: center;\"><img src=\"https://s2.showstart.com/img/2026/0320/12/00/801343045b2e470699a5390ccfce16b6_1080_1620_2037863.0x0.png?imageMogr2/thumbnail/640x/gravity/Center/crop/640x\" alt=\"\"></p>\n<p style=\"text-align: center;\">声音玩具以极具辨识度的艺术表达，成为当代摇滚领域里极具影响力的存在。音乐融合另类摇滚、艺术摇滚与迷幻摇滚，以诗意文本为骨，宏大编曲为翼，营造出深邃、辽阔且极具沉浸感的音乐氛围。他们以极致的艺术追求，不断突破摇滚的传统边界，用旋律与叙事构筑出充满哲思与诗意的精神世界。作为张冠李戴音乐节初代阵容，此次重磅回归，将再度以完整而成熟的现场美学，带来极具分量的舞台呈现。</p>\n<p style=\"text-align: center;\">&nbsp;</p>\n<h2 style=\"text-align: center;\"><span style=\"font-size: 24px;\"><strong><u>法兹FAZI</u></strong></span></h2>\n<p style=\"text-align: center;\"><img src=\"https://s2.showstart.com/img/2026/0320/12/00/9da02f4177ed41d3aa3e061a32cf8203_859_1289_2213643.0x0.png?imageMogr2/thumbnail/640x/gravity/Center/crop/640x\" alt=\"\"></p>\n<p style=\"text-align: center;\">西安本土标杆后朋克乐队，兼具国际视野。深耕冷峻而先锋的音乐表达。音乐融合德式泡菜摇滚、后朋克与迷幻摇滚特质，旋律诡谲灵动，器乐编排充满张力与对抗感。舞台之上以极具辨识度的形体美学与戏剧张力，构筑出自带东方神秘感、风格强烈的专属现场气场。</p>\n<p style=\"text-align: center;\">&nbsp;</p>\n<h2 style=\"text-align: center;\"><span style=\"font-size: 24px;\"><strong><u>南青</u></strong></span></h2>\n<p style=\"text-align: center;\"><img src=\"https://s2.showstart.com/img/2026/0320/12/00/3d86610f8b7641ff91e9eb68c04f4cdd_1080_1620_1481303.0x0.png?imageMogr2/thumbnail/640x/gravity/Center/crop/640x\" alt=\"\"></p>\n<p style=\"text-align: center;\">中原摇滚代表性青年乐队，作为华语摇滚新生代中极具号召力的中坚力量，以锐利又兼具思考的摇滚表达为内核，温暖叙事与旋律质感直抵人心。舞台之上能量充沛、冲击力十足，用音乐书写属于当代青年的鲜活摇滚注脚。</p>\n<p style=\"text-align: center;\">&nbsp;</p>\n<h2 style=\"text-align: center;\"><span style=\"font-size: 24px;\"><strong><u>贊詩</u></strong></span></h2>\n<p style=\"text-align: center;\"><img src=\"https://s2.showstart.com/img/2026/0320/12/00/bab04437aa384af7ad7f6e38fe1247ff_1080_1620_1866434.0x0.png?imageMogr2/thumbnail/640x/gravity/Center/crop/640x\" alt=\"\"></p>\n<p style=\"text-align: justify;\">来自河南郑州的新锐迷幻电子摇滚乐队，以多元融合为鲜明特质，将迷幻、电子、摇滚与民族音乐交织共生。他们把合成器的现代质感、民族乐器的传统韵味与民俗意象融为一体，形成极具表现力的视听反差。乐队以东方本土文化符号为基底，借传统意象观照当代生活，在旋律与节奏中完成对现实与精神世界的深刻思考，呈现兼具实验性与氛围感的现场舞台。</p>\n<p style=\"text-align: center;\">-</p>\n<p style=\"text-align: center;\"><strong><em>“Celebration in Rotation”</em></strong></p>\n<p style=\"text-align: center;\">在旋转中庆祝</p>\n<p style=\"text-align: center;\"><span style=\"color: #ba372a;\"><strong>演出时间表和票务信息近期公布</strong></span></p>\n<p style=\"text-align: center;\"><span style=\"color: #ba372a;\"><strong>敬请期待</strong></span></p>\n<p style=\"text-align: center;\">&nbsp;</p>\n<p style=\"text-align: center;\"><img src=\"https://s2.showstart.com/img/2026/0320/13/00/777c7f4acfae4749948f14d0e83fab15_500_500_108035.0x0.png?imageMogr2/thumbnail/640x/gravity/Center/crop/640x\" alt=\"\" width=\"640\" height=\"640\"></p>\n<h2 style=\"text-align: center;\"><strong><u>关于张冠李戴音乐节</u></strong></h2>\n<p style=\"text-align: center;\">2008年始创于西安</p>\n<p style=\"text-align: center;\">是中国最早的城市音乐节之一</p>\n<p style=\"text-align: center;\">2008年-2014年共举办七届</p>\n<p style=\"text-align: center;\">2015年-2025年停办十一载</p>\n<p style=\"text-align: center;\">2026年 归来仍是少年</p>"
    },
    {
        "event_id": "291444",
        "cover_image": "https://s2.showstart.com/img/2026/0313/17/30/98baa3f8cb32436ea08e0e97d287d5b8_1200_1600_1968820.0x0.jpg",
        "title": "2026济宁曲阜·新青年音乐节",
        "price": "¥198起",
        "time": "2026/04/18 14:00",
        "event_url": "https://www.showstart.com/event/291444",
        "artist": "椿乐队/贰佰/郝云/棱镜/米卡MIKA/麻园诗人/声音玩具/痛仰/野肆乐队",
        "address": "山东省济宁市曲阜市小雪街道阮家村亦乐田园(西南角)",
        "detail_time": "04月18日 14:00-04月18日 22:00",
        "venue": "济宁 曲阜市亦乐田园",
        "styles": [
            "流行",
            "摇滚",
            "民谣",
            "独立"
        ],
        "content_html": "<p><img src=\"https://s2.showstart.com/img/2026/0303/14/30/f80ce3cdf1224602aeb606d016697196_1080_1500_841167.0x0.jpg?imageMogr2/thumbnail/640x/gravity/Center/crop/640x\" alt=\"\"><img src=\"https://s2.showstart.com/img/2026/0313/17/30/29ba9bebfdc44449a88675b7f90f1dbc_1080_1720_1828815.0x0.jpg?imageMogr2/thumbnail/640x/gravity/Center/crop/640x\" alt=\"\" width=\"640\" height=\"1019\"><img src=\"https://s2.showstart.com/img/2026/0303/14/30/5384cf4c7fc94589a10dca8014c1ae42_1080_1520_1329065.0x0.jpg?imageMogr2/thumbnail/640x/gravity/Center/crop/640x\" alt=\"\"><img src=\"https://s2.showstart.com/img/2026/0303/14/30/c8a390a5a8b14ba58875c82387e47a94_1080_3080_2188144.0x0.jpg?imageMogr2/thumbnail/640x/gravity/Center/crop/640x\" alt=\"\"><img src=\"https://s2.showstart.com/img/2026/0303/14/30/df1a3c7e7d79438da7231c9fa931e005_1080_1480_867820.0x0.jpg?imageMogr2/thumbnail/640x/gravity/Center/crop/640x\" alt=\"\"></p>"
    },
    {
        "event_id": "293328",
        "cover_image": "https://s2.showstart.com/img/2026/0323/16/00/2b1e6df8695d4fb2b7a0b7326cc4ef05_1020_1360_1336089.0x0.jpg",
        "title": "【武汉】2026仙人掌音乐节",
        "price": "¥599起",
        "time": "2026/05/01 13:00",
        "event_url": "https://www.showstart.com/event/293328",
        "artist": "许巍/郑钧/痛仰/二手玫瑰乐队/老狼/棱镜/夏日入侵企画/张玮玮/郭龙/声音玩具/柳爽/散人/耿斯汉",
        "address": "湖北省武汉市黄陂区黄花涝路",
        "detail_time": "05月01日 13:00-05月01日 21:00",
        "venue": "武汉 武汉空港音乐广场",
        "styles": [
            "流行",
            "摇滚",
            "独立",
            "HipHop"
        ],
        "content_html": "<p><img src=\"https://s2.showstart.com/img/2026/0323/16/00/0045f018499f4df38d9d225e3a59597e_2976_4209_780885.0x0.png?imageMogr2/thumbnail/640x/gravity/Center/crop/640x\" alt=\"\"></p>\n<p>2026年5月1-3日<br>仙人掌音乐节，再度登陆武汉<br>“当多元音浪在荆楚大地交响”<br>“让此刻的共鸣直抵你我心脏”</p>\n<p><img src=\"https://s2.showstart.com/img/2026/0323/16/30/462e27c31bbf49898b0017d1e475555d_730_1701_1593816.0x0.png?imageMogr2/thumbnail/640x/gravity/Center/crop/640x\" alt=\"\"></p>\n<p>5月1日<br><br>★ 许巍<br>唱响诗意与远方</p>\n<p><img src=\"https://s2.showstart.com/img/2026/0323/16/30/22073af2c2ed47648f644fd348992697_1080_2180_2906466.0x0.png?imageMogr2/thumbnail/640x/gravity/Center/crop/640x\" alt=\"\"></p>\n<p>★ 郑钧<br>中国摇滚乐代表人物<br>归来仍是那个赤裸裸的</p>\n<p><img src=\"https://s2.showstart.com/img/2026/0323/16/30/ecbfa71fc5484b7cb5f66e91d22f8bd3_1080_2180_2978107.0x0.png?imageMogr2/thumbnail/640x/gravity/Center/crop/640x\" alt=\"\"></p>\n<p>★ 痛仰<br>中国摇滚的精神旗帜<br>一直往南方开，开到武汉</p>\n<p><img src=\"https://s2.showstart.com/img/2026/0323/16/30/04679d84b24f4d5c85d2d5ce446c0066_1080_2180_3209798.0x0.png?imageMogr2/thumbnail/640x/gravity/Center/crop/640x\" alt=\"\" width=\"640\" height=\"1292\"></p>\n<p>★ 二手玫瑰<br>摇滚江湖的一枝独秀<br>五一假期 武汉“接客</p>\n<p><img src=\"https://s2.showstart.com/img/2026/0323/16/30/bd85a5e31acd4777aa34c9fb53a43735_1080_2180_3930973.0x0.png?imageMogr2/thumbnail/640x/gravity/Center/crop/640x\" alt=\"\"></p>\n<p>★ 老狼<br>校园民谣的代言人<br>跨越青春的国民歌手</p>\n<p><img src=\"https://s2.showstart.com/img/2026/0323/16/30/2a81ccaef51b4c0789e54b88ba0006c9_1080_2180_3555076.0x0.png?imageMogr2/thumbnail/640x/gravity/Center/crop/640x\" alt=\"\"></p>\n<p>★ 棱镜<br>流动音阶组合纯粹词句<br>以真诚口吻表达真切情感</p>\n<p><img src=\"https://s2.showstart.com/img/2026/0323/16/30/d819286f9c3d483a9b0aa748b6b50601_1080_2180_2906020.0x0.png?imageMogr2/thumbnail/640x/gravity/Center/crop/640x\" alt=\"\"></p>\n<p>★ 夏日入侵企画<br>一起赴一场夏日的约<br>我们在武汉也可以一起“去海边”</p>\n<p><img src=\"https://s2.showstart.com/img/2026/0323/16/30/04795c6e3c9643a98636a3dce0522670_1080_2180_3945559.0x0.png?imageMogr2/thumbnail/640x/gravity/Center/crop/640x\" alt=\"\"></p>\n<p>★ 张玮玮＆郭龙<br>当代民谣代表性人物<br>携手把西北的风沙吹成诗</p>\n<p><img src=\"https://s2.showstart.com/img/2026/0323/16/30/46b6829abac443baa8d8cf941cd953c9_1080_2180_3490397.0x0.png?imageMogr2/thumbnail/640x/gravity/Center/crop/640x\" alt=\"\"></p>\n<p>★ 声音玩具<br>华丽而诗意的摇滚乐</p>\n<p><img src=\"https://s2.showstart.com/img/2026/0323/16/30/9ba5dc305a244e92bf09b2755eaa5176_1080_2180_2770038.0x0.png?imageMogr2/thumbnail/640x/gravity/Center/crop/640x\" alt=\"\"></p>\n<p>★ 柳爽<br>自由洒脱的年轻歌者</p>\n<p><img src=\"https://s2.showstart.com/img/2026/0323/16/30/8a85227a23c6460c82eca09db5191a16_1080_2180_3846830.0x0.png?imageMogr2/thumbnail/640x/gravity/Center/crop/640x\" alt=\"\"></p>\n<p>★ 散人乐队<br>川渝摇滚的符号级新人</p>\n<p><img src=\"https://s2.showstart.com/img/2026/0323/16/30/73b47404617341a690c6629e118a70ff_1080_2180_3511567.0x0.png?imageMogr2/thumbnail/640x/gravity/Center/crop/640x\" alt=\"\"></p>\n<p>★ 耿斯汉<br>华语乐坛的摇滚唱将</p>\n<p><img src=\"https://s2.showstart.com/img/2026/0323/16/30/ee4e924f26154e02850e41ee5a394878_1080_2180_3214799.0x0.png?imageMogr2/thumbnail/640x/gravity/Center/crop/640x\" alt=\"\"></p>\n<p>5月2日</p>\n<p>★ 张震岳<br>华语乐坛自在如风的唱作人<br>跟着感觉走的真实记录者</p>\n<p><img src=\"https://s2.showstart.com/img/2026/0323/16/30/263d415a1b2c4fddab5b9f3376c956aa_1080_2180_2738069.0x0.png?imageMogr2/thumbnail/640x/gravity/Center/crop/640x\" alt=\"\"></p>\n<p>★ 大张伟<br>人间清醒的朋克少年<br>永远真诚 永远传递快乐</p>\n<p><img src=\"https://s2.showstart.com/img/2026/0323/16/30/d8f26f5f85474cfe9956e7c7907e5b11_1080_2180_3396799.0x0.png?imageMogr2/thumbnail/640x/gravity/Center/crop/640x\" alt=\"\" width=\"640\" height=\"1292\"></p>\n<p>★ 林宥嘉<br>当代华语乐坛无法忽略的声音<br>温柔嗓音包裹的细致灵魂</p>\n<p><img src=\"https://s2.showstart.com/img/2026/0323/16/30/f64065e5a7574233b867721dfe111441_1080_2180_3444149.0x0.png?imageMogr2/thumbnail/640x/gravity/Center/crop/640x\" alt=\"\"></p>\n<p>★ 窦靖童<br>独具个性的华语女唱作人<br>在实验与流行的边界自由穿梭</p>\n<p><img src=\"https://s2.showstart.com/img/2026/0323/16/30/dde748b0a05943ccb24b912b2a07f937_1080_2180_2934053.0x0.png?imageMogr2/thumbnail/640x/gravity/Center/crop/640x\" alt=\"\" width=\"640\" height=\"1292\"></p>\n<p>★ 戴佩妮<br>华语乐坛公认的唱作才女<br>获奖无数的金曲天后</p>\n<p><img src=\"https://s2.showstart.com/img/2026/0323/16/30/7af9801fdd9c492eb24b66eb95572406_1080_2180_3441241.0x0.png?imageMogr2/thumbnail/640x/gravity/Center/crop/640x\" alt=\"\" width=\"640\" height=\"1292\"></p>\n<p>★ 魏如萱waa<br>是“末路狂花”也是“怪奇的珍珠”<br>抵达无数人心底的独特女声</p>\n<p><img src=\"https://s2.showstart.com/img/2026/0323/16/30/545b636942e4413bb90893db44c47194_1080_2180_3046312.0x0.png?imageMogr2/thumbnail/640x/gravity/Center/crop/640x\" alt=\"\"></p>\n<p>★ 杨乃文<br>特立独行的摇滚女爵<br>冷冽与炽热并存的另类女声</p>\n<p><img src=\"https://s2.showstart.com/img/2026/0323/16/30/6b8e52c8d6034047b5e68e1e8f8d7301_1080_2180_626551.0x0.jpg?imageMogr2/thumbnail/640x/gravity/Center/crop/640x\" alt=\"\" width=\"640\" height=\"1292\"></p>\n<p>★ 落日飞车<br>宝岛原创音乐旗舰型乐团<br>一辆驶向世界的音乐列车</p>\n<p><img src=\"https://s2.showstart.com/img/2026/0323/16/30/38a86a038fbe4818acd112cb5499b8b2_1080_2180_2800264.0x0.png?imageMogr2/thumbnail/640x/gravity/Center/crop/640x\" alt=\"\"></p>\n<p>★ 霓虹花园<br>年轻无畏的新浪漫主义乐队<br>用最具生命力的现场点燃空气</p>\n<p><img src=\"https://s2.showstart.com/img/2026/0323/16/30/59bd153f20e34baeba0517289972199f_1080_2180_3537205.0x0.png?imageMogr2/thumbnail/640x/gravity/Center/crop/640x\" alt=\"\"></p>\n<p>★ 艾怡良<br>岁月吻过的温柔女声<br>唱出都市人的隐秘心事</p>\n<p><img src=\"https://s2.showstart.com/img/2026/0323/16/30/b1be6779aafa429f88b327c854ae3322_1080_2180_3594515.0x0.png?imageMogr2/thumbnail/640x/gravity/Center/crop/640x\" alt=\"\" width=\"640\" height=\"1292\"></p>\n<p>★ ChiliChill乐团<br>极具创造力的二人音乐组合</p>\n<p><img src=\"https://s2.showstart.com/img/2026/0323/16/30/386bb70f416c4ae5b2e3dcf67eee7f3e_1080_2180_3309018.0x0.png?imageMogr2/thumbnail/640x/gravity/Center/crop/640x\" alt=\"\"></p>\n<p>★ 163braces<br>台湾Z世代创作女声<br>卧室里走出的超级新星</p>\n<p><img src=\"https://s2.showstart.com/img/2026/0323/16/30/c5316ccd2f054ff888d095ed7f330477_1080_2180_3293008.0x0.png?imageMogr2/thumbnail/640x/gravity/Center/crop/640x\" alt=\"\" width=\"640\" height=\"1292\"></p>\n<p>5月3日</p>\n<p>★ GAI周延（D.M.G）<br>新华流说唱领军人物</p>\n<p><img src=\"https://s2.showstart.com/img/2026/0323/16/30/5aad960decd548129683996e3d184ca2_1080_2180_3278010.0x0.png?imageMogr2/thumbnail/640x/gravity/Center/crop/640x\" alt=\"\" width=\"640\" height=\"1292\"></p>\n<p>★ C-BLOCK<br>「功夫胖KUNGFU-PEN / 盛宇D-SHINE / KEY.L刘聪」<br>湘江边走出的江湖传奇<br>把长沙刻入中文说唱版图<br><img src=\"https://s2.showstart.com/img/2026/0323/16/30/9d18f8d0ba6b4aefbaf869c47fb1afb6_1080_2180_2944116.0x0.png?imageMogr2/thumbnail/640x/gravity/Center/crop/640x\" alt=\"\"></p>\n<p>★ TizzyT<br>独具个性与天赋的音乐人<br>保持进化与蜕变的少年心气</p>\n<p><img src=\"https://s2.showstart.com/img/2026/0323/16/30/ed13778b86aa448b8ef736d94177e19c_1080_2180_3609268.0x0.png?imageMogr2/thumbnail/640x/gravity/Center/crop/640x\" alt=\"\"></p>\n<p>★ 姜云升<br>兼具Rap Star气质和超强实力<br>近年最具突破及关注度的说唱歌手<br><img src=\"https://s2.showstart.com/img/2026/0323/16/30/030d0f3afc704a83828f152ef75b43a4_1080_2180_3019989.0x0.png?imageMogr2/thumbnail/640x/gravity/Center/crop/640x\" alt=\"\"></p>\n<p>★ 沙一汀EL<br>才华横溢的少年说唱<br>用音乐记录Z世代情感</p>\n<p><img src=\"https://s2.showstart.com/img/2026/0323/16/30/72dac67ab3f3489f9e0144846c7ed645_1080_2180_3431403.0x0.png?imageMogr2/thumbnail/640x/gravity/Center/crop/640x\" alt=\"\"></p>\n<p>★ 艾志恒Asen<br>行业标杆级的说唱歌手<br>激励无数听众的小镇传奇</p>\n<p><img src=\"https://s2.showstart.com/img/2026/0323/16/30/04624147f28341b095865eba75d15016_1080_2180_3362215.0x0.png?imageMogr2/thumbnail/640x/gravity/Center/crop/640x\" alt=\"\"></p>\n<p>★ GALI<br>帅哥说唱代表<br>兼具先锋质感与街头态度<br><img src=\"https://s2.showstart.com/img/2026/0323/16/30/daa3d5f831c944109b2a1e9a0842ecab_1080_2180_3247055.0x0.png?imageMogr2/thumbnail/640x/gravity/Center/crop/640x\" alt=\"\"></p>\n<p>★ 王齐铭WatchMe<br>重庆说唱的中流砥柱<br>将市井生活熬成一锅“麻辣烫”</p>\n<p><img src=\"https://s2.showstart.com/img/2026/0323/16/30/3d8685799ffe4adf8822044dd8c0a19c_1080_2180_3427354.0x0.png?imageMogr2/thumbnail/640x/gravity/Center/crop/640x\" alt=\"\" width=\"640\" height=\"1292\"></p>\n<p>★ MULA SAKEE<br>浪潮之中保持真我<br>具有国际视野的Rap Star</p>\n<p><img src=\"https://s2.showstart.com/img/2026/0323/16/30/f1405625ee6b4e5ab56f9920db7f6a96_1080_2180_3154249.0x0.png?imageMogr2/thumbnail/640x/gravity/Center/crop/640x\" alt=\"\" width=\"640\" height=\"1292\"></p>\n<p>★ Top Barry<br>2025最受瞩目的新生代Rapper<br>试图用年轻视角重新定义潮流</p>\n<p><img src=\"https://s2.showstart.com/img/2026/0323/16/30/b3fca31418b94d018b6b00c8272abb8e_1080_2180_3668902.0x0.png?imageMogr2/thumbnail/640x/gravity/Center/crop/640x\" alt=\"\"></p>\n<p>★华云龙KLE<br>中文方言说唱现象级黑马<br>短视频平台爆火的“山东王”</p>\n<p><img src=\"https://s2.showstart.com/img/2026/0323/16/30/2417469ed149440fa1314fc029d907ca_1080_2180_3117747.0x0.png?imageMogr2/thumbnail/640x/gravity/Center/crop/640x\" alt=\"\"></p>\n<p>★ 翁杰 Winjay<br>福建沿海走出的“莆田才子”<br>在城乡之间重构街头叙事</p>\n<p><img src=\"https://s2.showstart.com/img/2026/0323/16/30/6546ade6c43e4366827cf7bdbb2ccd06_1080_2180_3499619.0x0.png?imageMogr2/thumbnail/640x/gravity/Center/crop/640x\" alt=\"\"></p>\n<p>★ 陈一豪Clear<br>真诚叙事的治愈系少年<br>让长沙再次骄傲的实力新生代</p>\n<p><img src=\"https://s2.showstart.com/img/2026/0323/16/30/7cb968ca4724458f9934f12e17eff253_1080_2180_3837418.0x0.png?imageMogr2/thumbnail/640x/gravity/Center/crop/640x\" alt=\"\"></p>\n<p>★ 马赫mood<br>左手拿起画笔 &nbsp;右手拿起麦克风<br>街头画家用真实经历打磨每一个韵脚</p>\n<p><img src=\"https://s2.showstart.com/img/2026/0323/16/30/407addc5936e44e58ab77c6dd8e456e0_1080_2180_2942322.0x0.png?imageMogr2/thumbnail/640x/gravity/Center/crop/640x\" alt=\"\"></p>\n<p>（ACID）</p>\n<p>★ 极品贵公子 ＆ Udigg&amp;贾真 ＆ Africakid中文说唱新血代表</p>\n<p><img src=\"https://s2.showstart.com/img/2026/0323/16/30/aae7732253a54730a69d0a169cc5e986_1080_2180_3541507.0x0.png?imageMogr2/thumbnail/640x/gravity/Center/crop/640x\" alt=\"\"></p>"
    },
    {
        "event_id": "289736",
        "cover_image": "https://s2.showstart.com/img/2026/0325/14/00/bf56d56945aa4668b2e2bf993065c635_2500_3334_2410899.0x0.jpg",
        "title": "2026 泡泡岛音乐与艺术节·京津冀站",
        "price": "¥399起",
        "time": "2026/05/02 12:30",
        "event_url": "https://www.showstart.com/event/289736",
        "artist": "万能青年旅店/痛仰/逃跑计划/Black Country, New Road/Sea Power/Motorama/YUFU/夏日入侵企画/刘忻/遗忘俱乐部/Bonobo",
        "address": "天津市滨海新区",
        "detail_time": "05月02日 12:30-05月02日 21:00",
        "venue": "天津 东疆亲海音乐广场",
        "styles": [
            "流行",
            "摇滚",
            "HipHop"
        ],
        "content_html": "<p><img src=\"https://s2.showstart.com/img/2026/0326/10/30/06e2c8bb55b64ce680793ac919e99b89_843_799_80752.0x0.png?imageMogr2/thumbnail/640x/gravity/Center/crop/640x\" alt=\"\" width=\"640\" height=\"607\"><img src=\"https://s2.showstart.com/img/2026/0326/10/30/621d531ebf974347b03e3ce175a0ea58_1563_1761_357405.0x0.png?imageMogr2/thumbnail/640x/gravity/Center/crop/640x\" alt=\"\" width=\"640\" height=\"721\"><img src=\"https://s2.showstart.com/img/2026/0326/10/30/015a81d443404af3bdd258d87c7a3bb0_1563_5667_1225379.0x0.png?imageMogr2/thumbnail/640x/gravity/Center/crop/640x\" alt=\"\" width=\"640\" height=\"2320\"><img src=\"https://s2.showstart.com/img/2026/0326/10/30/a251d93d23914924a9d7aa4686444739_1563_2647_485783.0x0.png?imageMogr2/thumbnail/640x/gravity/Center/crop/640x\" alt=\"\" width=\"640\" height=\"1084\"><img src=\"https://s2.showstart.com/img/2026/0326/10/30/9e19e2ec510f4255b7de294143dad8ce_1563_4222_927426.0x0.png?imageMogr2/thumbnail/640x/gravity/Center/crop/640x\" alt=\"\" width=\"640\" height=\"1729\"><img src=\"https://s2.showstart.com/img/2026/0326/12/00/5d6dc2c7f19746e1a1b7d2668f511b9b_1279_3160_528220.0x0.jpg?imageMogr2/thumbnail/640x/gravity/Center/crop/640x\" alt=\"\" width=\"640\" height=\"1581\"><img src=\"https://s2.showstart.com/img/2026/0326/10/30/b76b1ef6a8f6481bb374e30befe4529a_1100_460_60444.0x0.jpg?imageMogr2/thumbnail/640x/gravity/Center/crop/640x\" alt=\"\" width=\"640\" height=\"268\"><img src=\"https://s2.showstart.com/img/2026/0326/14/00/2d6843cb7bb34d19808f22e5f027374a_1080_13000_1676659.0x0.jpg?imageMogr2/thumbnail/640x/gravity/Center/crop/640x\" alt=\"\" width=\"640\" height=\"7704\"><img src=\"https://s2.showstart.com/img/2026/0326/14/00/bbcedfec79e349f9841d8bca8168ec9a_1170_13334_9656967.0x0.jpg?imageMogr2/thumbnail/640x/gravity/Center/crop/640x\" alt=\"\" width=\"640\" height=\"7294\"><img src=\"https://s2.showstart.com/img/2026/0326/14/00/1b7d121f7b374996b270dc54a56dbe04_1080_9010_911203.0x0.jpg?imageMogr2/thumbnail/640x/gravity/Center/crop/640x\" alt=\"\" width=\"640\" height=\"5339\"></p>"
    },
    {
        "event_id": "293488",
        "cover_image": "https://s2.showstart.com/img/2026/0325/11/00/8ed0c770e9b447bf9632696a80a73a9a_1020_1360_837676.0x0.jpg",
        "title": "2026东莞超级草莓音乐节",
        "price": "¥329起",
        "time": "2026/05/02 13:30",
        "event_url": "https://www.showstart.com/event/293488",
        "artist": "陈粒/万妮达/蔡健雅/陈珊妮/徐佳莹/颜人中/房东的猫/棱镜/阿肆/余佳运/陈婧霏/Matt吕彦良",
        "address": "东莞市松山湖新城大道中心公园内",
        "detail_time": "05月02日 13:30-05月02日 22:00",
        "venue": "东莞 松山湖中心公园大草坪",
        "styles": [
            "流行",
            "摇滚"
        ],
        "content_html": "<p><img style=\"display: block; margin-left: auto; margin-right: auto;\" src=\"https://s2.showstart.com/img/2026/0325/11/00/03fa128ca17e4355be9d7abafe567fa4_1080_442_382363.0x0.png?imageMogr2/thumbnail/640x/gravity/Center/crop/640x\" alt=\"\" width=\"640\" height=\"262\"></p>\n<p style=\"text-align: center;\"><strong>为了保障您的权益实现并获得良好的观演体验，请您向下滑动，继续完整阅读理解本页面所有内容后再进行门票购买或使用。</strong></p>\n<p style=\"text-align: center;\"><strong>⬇</strong></p>\n<p style=\"text-align: center;\"><strong>&nbsp;</strong></p>\n<p style=\"text-align: justify;\"><strong>1.订单支付成功后，不支持修改观演日期、观演人、票种等信息。</strong></p>\n<p style=\"text-align: justify;\"><strong>2.个人实名制门票，仅限订单内登记的观演人本人使用，转赠或转售他人使用将无法入场。</strong></p>\n<p style=\"text-align: justify;\"><strong>3.演出现场均为站立观演，不设座位，门票仅限一次进出，中途离场后将无法再次入场。</strong></p>\n<p style=\"text-align: justify;\"><strong>4.如无法如期观看演出，请提前查阅公示的退票规则并按照退票规则申请退票，退票时间截止后无法受理退票请求。</strong></p>\n<p style=\"text-align: justify;\"><strong>5.任何购买或使用门票行为，视为已阅读理解本文须知内容，购买或使用前请再三阅读理解本页面介绍。</strong></p>\n<p style=\"text-align: center;\">&nbsp;</p>\n<p style=\"text-align: center;\">&nbsp;</p>\n<p style=\"text-align: center;\"><strong>【关于演出艺人及演出时间】</strong></p>\n<p style=\"text-align: center;\"><strong><img src=\"https://s2.showstart.com/img/2026/0325/11/00/35be6634d87942cdb5ff718e5eaf520e_1020_2526_1321235.0x0.png?imageMogr2/thumbnail/640x/gravity/Center/crop/640x\" alt=\"\"></strong></p>\n<p style=\"text-align: center;\"><strong><img src=\"https://s2.showstart.com/img/2026/0325/11/00/bc1b4d4b79c64855a17357202bb0e993_522_1412_615936.0x0.png?imageMogr2/thumbnail/640x/gravity/Center/crop/640x\" alt=\"\" width=\"640\" height=\"1731\"></strong></p>\n<p>&nbsp;</p>\n<p style=\"text-align: center;\"><strong>【关于门票及票价】</strong></p>\n<p style=\"text-align: justify;\">学生单日票329元：≤25周岁全日制在校学生，检票入场时需持本人有效学生证件。（无有效证件须按照全价单日票补全差价）；</p>\n<p style=\"text-align: justify;\">预售单日票399元；</p>\n<p style=\"text-align: justify;\">全价单日票499元；</p>\n<p style=\"text-align: justify;\">优享单日票599元：含音乐节单日票门票1张，以及专属权益（草莓舞台和爱舞台前排观演；专属检票通道；优先30分钟检票入场；官方指定饮品×1；官方特定周边8折）；</p>\n<p style=\"text-align: justify;\">PRO单日票799元：含音乐节单日票门票1张，以及专属礼包、专属权益。（专属礼包：二合一功能包 ×1、随机官方CD ×1、Modern气囊支架×1；专属权益：草莓舞台和爱舞台前排观演；独立休息区；专属快速检票通道；优先30分钟检票入场；官方指定饮品×2；专属存包处；独立卫生间；充电处；彩绘区。）</p>\n<p style=\"text-align: justify;\">预售单人两日通票758元（379元*2天）：任选2日，单日仅限1次入场。</p>\n<p style=\"text-align: justify;\">预售单人三日通票1077元（359元*3天）：5月2日、3日、4日，单日仅限1次入场。</p>\n<p style=\"text-align: justify;\">&nbsp;</p>\n<p style=\"text-align: center;\"><span style=\"color: #e03e2d;\"><strong>*购买PRO票、优享票的观众请检票入场后根据导示前往「手环兑换/门票升级」区兑换并完全佩戴专属手环，凭手环享受相关权益。</strong></span></p>\n<p style=\"text-align: center;\"><strong><img src=\"https://s2.showstart.com/img/2026/0325/11/00/5486ab30e90f4493beaf03275c1a623f_539_2119_492039.0x0.png?imageMogr2/thumbnail/640x/gravity/Center/crop/640x\" alt=\"\"></strong></p>\n<p style=\"text-align: center;\"><strong>【关于购票】</strong></p>\n<p>1.请选择从官方售票平台购票，切勿盲目相信二手交易、代刷代抢等一切非官方途径获取门票，一切从非官方售票途径获取门票产生的后果均由个人承担。</p>\n<p>2.<span style=\"color: #e03e2d;\">本场演出门票为实名制身份证电子票，一票一证，无纸质门票。</span>可提前通过官方售票平台录入观演人信息，以便快捷购票。购票时请再三确认好购买日期、票种、观演人等重要信息，避免信息错误无法入场。</p>\n<p>3.支付成功后，不支持更换观演日期、观演人，个人门票仅限订单内登记的观演人本人使用。如因购票时填写的观演信息有误、转增或转售门票导致无法入场，需自行承担责任。</p>\n<p>4.<span style=\"color: #e03e2d;\">一个日期对应一个证件仅限持有1张门票，请不要使用同一个证件在多个平台重复购买同一日期门票。</span>若产生无效的重复订单，票务平台有权对此订单整体取消，仅保留一笔订单。且重复订单需整单整退，无法拆单退票，并收取整单付款金额的30%作为退票手续费，因此重复购票产生的费用，或无法入场观演等一切损失由购票人及观演人自行承担。</p>\n<p>5.<span style=\"color: #e03e2d;\">未成年人购票前请获得法定监护人同意，若购票订单成功生成并完成支付,视为已经过法定监护人准许购票。</span>由此产生的法律责任由其法定监护人承担，与票务平台、主办方无关。如需退票请按照统一退票规则执行。</p>\n<p><strong>&nbsp;</strong></p>\n<p style=\"text-align: center;\"><strong>【关于退票】</strong></p>\n<p>本次音乐节于03月31日11:00正式开启门票预售，预售开售后，订单支付完成后视为购票成功：</p>\n<p>2026年4月2日11:00之前，可无条件办理退票。</p>\n<p>2026年4月2日11:00-4月4日11:00，此期间申请退票收取订单实际付款金额20%的手续费。</p>\n<p>2026年4月4日11:00-4月24日11:00，此期间申请退票收取订单实际付款金额30%的手续费。</p>\n<p>2026年4月24日11:00之后，不支持退票，不再接收退票请求。</p>\n<p>&nbsp;</p>\n<p>退票仅支持整单整退，同一订单下的多张门票不支持拆分退票。</p>\n<p>退票门票将返回官方售票平台继续销售，<span style=\"color: #e03e2d;\"><strong>同一购票人、同一个购票账户，在产生一次退票后请谨慎购买，再次购买同场次票后不再享有退票权益。</strong></span></p>\n<p>如需退票，请联系原购票平台，在客服工作人员正常工作时间内进行申请，申请方式、退款到账时间以各平台规则为准。</p>\n<p>&nbsp;</p>\n<p>&nbsp;</p>\n<p style=\"text-align: center;\"><strong>【关于安检及入场】</strong></p>\n<p><strong>为保障大型群众性活动安全，请您务必清楚以下禁限带物品，请勿携带入场：</strong></p>\n<p>*禁止携带冷焰火、烟雾棒（罐）、烟饼等各类可燃&amp;冒烟物品、旗杆和各类旗帜/横幅/条幅/标语/传单（包括任何伸缩旗帜旗杆）、酒精或含酒精成分饮品、打火机。</p>\n<p>*禁止携带非密封包装食品（如零食、快餐、水果等非密封包装或已拆封食品）。</p>\n<p>*禁止携带大型或硬质坐卧休息物品（如塑料/金属凳子、大型充气床垫、其他折叠桌/椅）。</p>\n<p>*禁止携带长柄雨伞（可自备其他轻便雨具，如小型折叠伞、雨衣等）。</p>\n<p>*禁止携带硬质发光灯牌、可投掷发光发声应援物、充气物（气球/气棒）、航拍飞行器、专业摄录设备（单反或长焦镜头长度超10厘米）、自拍杆（含三脚架）。</p>\n<p>*禁止携带各类型号材质饮品容器（金属、玻璃、瓶装、罐装、袋装等），自带饮品入场流程繁琐，体验欠佳，安检容易拥堵。若自带饮品请在安检前【饮品-免费换杯点】将饮品倒入官方定制的免费水杯后并在安检前试喝无问题方可带入，饮品容器请自弃或寄存。</p>\n<p>&nbsp;</p>\n<p><strong>其他禁限带物品及须知：</strong></p>\n<p>1.禁止携带宠物（导盲犬除外）、大件行李（超过50*36*20cm）、马克笔、油漆笔、激光笔、水枪、玩具枪、仿真枪、自行车、平衡车、滑板、轮滑、帐篷天幕、露营车。</p>\n<p>2.禁止携带穿戴有敏感性政治性侮辱性的服装/饰品/帽子/鞋子等物品。严禁将烟花、爆竹、火柴、管制刀具、枪支弹药、散装药品、违禁药品、液压罐装防晒以及其他罐装喷雾类产品、易投掷物品、以及含酒精化妆品在内的常规易燃易爆危险物品。</p>\n<p>3.其他国家法定禁止携带物品、大型活动禁止限制携带物品。</p>\n<p>4.禁限带物品以现场安检要求为准，请协助和配合安检人员的要求。违规者则可能涉嫌违反《大型群众性活动安全管理条例》。对违反规定的团体与个人，现场安保和相关工作人员有权利制止或责令退场。</p>\n<p>&nbsp;</p>\n<p>为了保障您的入场体验，请务必携带身份证原件入场。无身份证的未成年人需携带户口本核验入场。登记其他有效证件类型购票成功的观众，请本人携带有效证件原件核验入场。</p>\n<p>&nbsp;</p>\n<p>如因购票时填写的观演信息有误、通过非官方售票途径获取门票导致无法入场，需<strong>自行承担责任</strong>。</p>\n<p>&nbsp;</p>\n<p>每日演出时间为：13:30-21:30。正在现场登登登VIP、PRO票、优享票观众入场时间为：12:00，其余观众入场时间为：12:30，观众最晚入场时间为：20:30。受现场各类突发情况等不可控因素影响，演出时间时长和入场时间请以现场实际发生为准，请提前规划好出行时间。<span style=\"color: #e03e2d;\"><strong>本场演出均为站席观演，不设座位</strong>。</span></p>\n<p>&nbsp;</p>\n<p><span style=\"color: #e03e2d;\"><strong>重要提示：身份证电子票仅限本人使用，单天仅限一次使用，出场后无法再次入场。</strong></span></p>\n<p>&nbsp;</p>\n<p style=\"text-align: center;\"><strong>【关于其他】</strong></p>\n<p><strong>免票政策：</strong>1.2米以下儿童可在已购票家长（监护人）陪同下免票入场，每位家长（监护人）限携带一位儿童。</p>\n<p>&nbsp;</p>\n<p><strong>特别提醒：</strong>音乐节现场人员相对较多，家长需自行看管好儿童。音乐节现场音响声音较大，6岁以下婴幼儿不建议入场，避免造成听力损伤。</p>\n<p>&nbsp;</p>\n<p>任何购买、持有或使用门票的观众均被认为已经阅读、理解并接受本须知。所有入场者，均被视为同意被主办方拍摄、录影并传播。</p>\n<p>&nbsp;</p>\n<p>音乐节现场请注意人身财产安全，文明观演，禁止乱扔垃圾，请自觉保护场地卫生环境，禁止翻越护栏等隔离设施，禁止向舞台投掷任何物品，演出结束后，请按照现场指引和工作人员引导有序退场，请勿拥挤、逗留。如遇紧急情况请立刻联系现场安保人员或前往乐迷服务中心寻求帮助。</p>\n<p>&nbsp;</p>\n<p>&nbsp;</p>"
    },
    {
        "event_id": "291139",
        "cover_image": "https://s2.showstart.com/img/2026/0313/20/00/44aeac39c9274b44bf56ab6165aab795_2126_2834_2728741.0x0.jpg",
        "title": "2026葫芦果音乐节·合肥站",
        "price": "¥368起",
        "time": "2026/05/03 13:00",
        "event_url": "https://www.showstart.com/event/291139",
        "artist": "痛仰/二手玫瑰乐队/梁博/范晓萱/安溥ANPU/房东的猫/旅行团/刺猬Hedgehog/霓虹花园/盘尼西林",
        "address": "安徽省合肥市包河区包河大道骆岗公园梦想大草坪北段",
        "detail_time": "05月03日 13:00-05月03日 22:00",
        "venue": "合肥 合肥骆岗公园梦想大草坪",
        "styles": [
            "流行",
            "摇滚",
            "独立",
            "民谣",
            "HipHop"
        ],
        "content_html": "<p><img src=\"https://s2.showstart.com/img/2026/0327/10/30/45c59f30c8ae4b51ae7c575677a228da_2251_12641_8917937.0x0.jpg?imageMogr2/thumbnail/640x/gravity/Center/crop/640x\" alt=\"\" width=\"640\" height=\"3594\"><img src=\"https://s2.showstart.com/img/2026/0327/10/30/f6fa308de9c448b6aed81d266f46c5b6_1279_7687_1060003.0x0.jpg?imageMogr2/thumbnail/640x/gravity/Center/crop/640x\" alt=\"\"></p>"
    },
    {
        "event_id": "292537",
        "cover_image": "https://s2.showstart.com/img/2026/0316/21/00/bfa9ee0055314cdda8df23ab998a80fc_1200_1600_471020.0x0.jpg",
        "title": "2026 长春哦啦音乐节·向北之旅",
        "price": "¥298起",
        "time": "2026/05/23 13:30",
        "event_url": "https://www.showstart.com/event/292537",
        "artist": "新裤子/安溥ANPU/陈粒/逃跑计划/声音玩具/棱镜/刘忻/遗忘俱乐部/陈婧霏/许钧/YUFU/耿斯汉",
        "address": "永春街777号",
        "detail_time": "05月23日 13:30-05月23日 21:30",
        "venue": "长春 长春东北亚国际博览中心",
        "styles": [
            "摇滚",
            "独立"
        ],
        "content_html": "<p><img src=\"https://s2.showstart.com/img/2026/0316/21/00/2f6f05db85ae49afb721219f67b92eee_3508_3066_519269.0x0.png?imageMogr2/thumbnail/640x/gravity/Center/crop/640x\" alt=\"\"></p>\n<p><img src=\"https://s2.showstart.com/img/2026/0316/21/00/247cafa71f03455387533c97d32c0a51_1080_4727_3537134.0x0.png?imageMogr2/thumbnail/640x/gravity/Center/crop/640x\" alt=\"\"></p>\n<p><img src=\"https://s2.showstart.com/img/2026/0325/10/30/041dc746259249039b593dab29fee23b_2250_9073_3718557.0x0.jpg?imageMogr2/thumbnail/640x/gravity/Center/crop/640x\" alt=\"\" width=\"640\" height=\"2581\"></p>\n<p><img src=\"https://s2.showstart.com/img/2026/0316/21/00/4ef55f3a90a74e52941a072cfc49cd28_1081_1920_1045902.0x0.jpg?imageMogr2/thumbnail/640x/gravity/Center/crop/640x\" alt=\"\" width=\"640\" height=\"1137\"></p>\n<p><img src=\"https://s2.showstart.com/img/2026/0316/21/00/e3a8e8c4c052456797db287cd5cca7d8_1080_1776_933132.0x0.png?imageMogr2/thumbnail/640x/gravity/Center/crop/640x\" alt=\"\"></p>\n<p><img src=\"https://s2.showstart.com/img/2026/0316/21/00/a4ee318cce7247b9b362b32296b43413_1280_1037_112232.0x0.jpg?imageMogr2/thumbnail/640x/gravity/Center/crop/640x\" alt=\"\" width=\"640\" height=\"519\"></p>\n<p><img src=\"https://s2.showstart.com/img/2026/0316/21/00/e0a232d24ce24a69b0ed543ab38edf25_1280_2148_218230.0x0.jpg?imageMogr2/thumbnail/640x/gravity/Center/crop/640x\" alt=\"\" width=\"640\" height=\"1074\"></p>\n<p><img src=\"https://s2.showstart.com/img/2026/0316/21/00/aa0eb6b44c3a409e9e690c9860efc411_1280_1735_161463.0x0.jpg?imageMogr2/thumbnail/640x/gravity/Center/crop/640x\" alt=\"\" width=\"640\" height=\"868\"></p>\n<p><img src=\"https://s2.showstart.com/img/2026/0316/21/00/b3b8e5f776e44e298a4c9e7455c579d6_1280_1774_192288.0x0.jpg?imageMogr2/thumbnail/640x/gravity/Center/crop/640x\" alt=\"\"></p>\n<p><img src=\"https://s2.showstart.com/img/2026/0316/21/00/013a9604fc7042b697477b31471f7098_1280_668_58300.0x0.jpg?imageMogr2/thumbnail/640x/gravity/Center/crop/640x\" alt=\"\" width=\"640\" height=\"334\"></p>\n<p><img src=\"https://s2.showstart.com/img/2026/0316/21/00/3d7fb69c7d044378b4a11ecf35f36e30_1280_1337_124091.0x0.jpg?imageMogr2/thumbnail/640x/gravity/Center/crop/640x\" alt=\"\"></p>"
    },
    {
        "event_id": "293387",
        "cover_image": "https://s2.showstart.com/img/2026/0324/10/30/695709b982cc4a21a90fa8402b7aa3e7_1200_1600_1346327.0x0.jpg",
        "title": "金辰地产·2026德州天衢新区新青年音乐节",
        "price": "¥161起",
        "time": "2026/05/30 14:00",
        "event_url": "https://www.showstart.com/event/293387",
        "artist": "许巍/新裤子/旅行团/马頔/隔壁老樊/岛屿心情/许钧/A公馆/闪星TWINKLESTAR",
        "address": "山东省德州市德城区崇德八大道5939号",
        "detail_time": "05月30日 14:00-05月30日 22:00",
        "venue": "德州 德州天衢新区万人广场（德州工程职业学院南侧）",
        "styles": [
            "流行",
            "摇滚",
            "独立"
        ],
        "content_html": "<p><img src=\"https://s2.showstart.com/img/2026/0324/10/30/34c319efa1134528a012dad6f952b729_1080_1250_422581.0x0.jpg?imageMogr2/thumbnail/640x/gravity/Center/crop/640x\" alt=\"\" width=\"640\" height=\"741\"><img src=\"https://s2.showstart.com/img/2026/0324/10/30/173e20a0cd4c4edd9cb342ffe37d910c_1080_1600_1018093.0x0.jpg?imageMogr2/thumbnail/640x/gravity/Center/crop/640x\" alt=\"\" width=\"640\" height=\"948\"><img src=\"https://s2.showstart.com/img/2026/0324/10/30/1e3165a5c62e45dea91cea94b0e8e45a_1080_2100_988174.0x0.jpg?imageMogr2/thumbnail/640x/gravity/Center/crop/640x\" alt=\"\"><img src=\"https://s2.showstart.com/img/2026/0324/10/30/78c2decccebe46eab1266ee19f3f658b_1080_2150_1189668.0x0.jpg?imageMogr2/thumbnail/640x/gravity/Center/crop/640x\" alt=\"\"><img src=\"https://s2.showstart.com/img/2026/0324/10/30/19538985beca4e4ea7e6f2e82184a8c2_1080_1600_697096.0x0.jpg?imageMogr2/thumbnail/640x/gravity/Center/crop/640x\" alt=\"\"></p>"
    }
]